{
    "ResearchInstitution": "VU",
    "ParticipantName": "p29",
    "TrialNumber": 184,
    "DateTime": "2022_5_13_16_01_46",
    "VideoName": "Null",
    "VideoHeight": 1.0,
    "VideoWidth": 7.300000190734863,
    "GoalkeeperStartBeforeKick": 0.0,
    "GoalkeeperDisplacement": 0.0,
    "AdvertisementStartBeforeKick": 10.0,
    "BallElasticity": 2.0,
    "JumpDirection": "Left",
    "AdvertisementDirection": "None",
    "Events": {
        "Start": {
            "Origin": {
                "X": 0.02147229015827179,
                "Y": 0.1454663723707199,
                "Z": -0.14788158237934113
            },
            "VelocityVector": {
                "X": 0.07238548249006272,
                "Y": 0.05450214445590973,
                "Z": 0.36578381061553957
            }
        },
        "End": {
            "EndLocation": {
                "X": 2.246375322341919,
                "Y": 0.1100013330578804,
                "Z": 11.351434707641602
            }
        },
        "Dive": {}
    },
    "Tracking": {
        "Foot": [
            {
                "X": -0.021193742752075197,
                "Y": 0.13381290435791017,
                "Z": -0.5518738031387329
            },
            {
                "X": -0.026766300201416017,
                "Y": 0.1348261833190918,
                "Z": -0.5554341077804565
            },
            {
                "X": -0.031354665756225589,
                "Y": 0.1447141170501709,
                "Z": -0.5616282224655151
            },
            {
                "X": -0.03363513946533203,
                "Y": 0.14452290534973145,
                "Z": -0.569438099861145
            },
            {
                "X": -0.03198575973510742,
                "Y": 0.1446695327758789,
                "Z": -0.5729357004165649
            },
            {
                "X": -0.0320436954498291,
                "Y": 0.1452803611755371,
                "Z": -0.575344443321228
            },
            {
                "X": -0.03499197959899902,
                "Y": 0.14683055877685548,
                "Z": -0.576720118522644
            },
            {
                "X": -0.034689903259277347,
                "Y": 0.14648890495300294,
                "Z": -0.5788711309432983
            },
            {
                "X": -0.03462696075439453,
                "Y": 0.14578032493591309,
                "Z": -0.5798932313919067
            },
            {
                "X": -0.035367727279663089,
                "Y": 0.1457512378692627,
                "Z": -0.580525279045105
            },
            {
                "X": -0.03526663780212402,
                "Y": 0.14560985565185548,
                "Z": -0.5823031663894653
            },
            {
                "X": -0.0355992317199707,
                "Y": 0.14638042449951173,
                "Z": -0.5830696821212769
            },
            {
                "X": -0.03505086898803711,
                "Y": 0.14637279510498048,
                "Z": -0.5843287706375122
            },
            {
                "X": -0.03478527069091797,
                "Y": 0.14648175239562989,
                "Z": -0.5857928991317749
            },
            {
                "X": -0.035414695739746097,
                "Y": 0.14723753929138184,
                "Z": -0.5858911275863648
            },
            {
                "X": -0.03583383560180664,
                "Y": 0.14723896980285645,
                "Z": -0.5859521627426148
            },
            {
                "X": -0.03559112548828125,
                "Y": 0.14693570137023927,
                "Z": -0.5852810144424439
            },
            {
                "X": -0.03603363037109375,
                "Y": 0.14722728729248048,
                "Z": -0.5842493772506714
            },
            {
                "X": -0.03593778610229492,
                "Y": 0.14721274375915528,
                "Z": -0.5841821432113648
            },
            {
                "X": -0.03598475456237793,
                "Y": 0.14754915237426759,
                "Z": -0.5838433504104614
            },
            {
                "X": -0.03587961196899414,
                "Y": 0.1476438045501709,
                "Z": -0.5837875604629517
            },
            {
                "X": -0.03601431846618652,
                "Y": 0.14762282371520997,
                "Z": -0.5836607217788696
            },
            {
                "X": -0.03604531288146973,
                "Y": 0.14776110649108888,
                "Z": -0.5834895372390747
            },
            {
                "X": -0.036108970642089847,
                "Y": 0.14790558815002442,
                "Z": -0.583476185798645
            },
            {
                "X": -0.03615140914916992,
                "Y": 0.14776921272277833,
                "Z": -0.5832823514938355
            },
            {
                "X": -0.03625941276550293,
                "Y": 0.14794158935546876,
                "Z": -0.5833271741867065
            },
            {
                "X": -0.036364078521728519,
                "Y": 0.14782285690307618,
                "Z": -0.583217978477478
            },
            {
                "X": -0.03635811805725098,
                "Y": 0.14791131019592286,
                "Z": -0.5834485292434692
            },
            {
                "X": -0.03621625900268555,
                "Y": 0.14797592163085938,
                "Z": -0.5836440324783325
            },
            {
                "X": -0.03645205497741699,
                "Y": 0.14825701713562013,
                "Z": -0.5835663080215454
            },
            {
                "X": -0.03645205497741699,
                "Y": 0.14825701713562013,
                "Z": -0.5835663080215454
            },
            {
                "X": -0.03649258613586426,
                "Y": 0.14840388298034669,
                "Z": -0.5838140249252319
            },
            {
                "X": -0.036431074142456058,
                "Y": 0.14862322807312013,
                "Z": -0.5838264226913452
            },
            {
                "X": -0.03636360168457031,
                "Y": 0.1487276554107666,
                "Z": -0.5840328931808472
            },
            {
                "X": -0.03640031814575195,
                "Y": 0.14882826805114747,
                "Z": -0.5842934846878052
            },
            {
                "X": -0.03647923469543457,
                "Y": 0.14913702011108399,
                "Z": -0.5842965841293335
            },
            {
                "X": -0.03681826591491699,
                "Y": 0.14859724044799806,
                "Z": -0.5838004350662231
            },
            {
                "X": -0.0366969108581543,
                "Y": 0.14863872528076173,
                "Z": -0.5839389562606812
            },
            {
                "X": -0.036594390869140628,
                "Y": 0.14876818656921388,
                "Z": -0.584100604057312
            },
            {
                "X": -0.036443471908569339,
                "Y": 0.1488475799560547,
                "Z": -0.5842794179916382
            },
            {
                "X": -0.0366673469543457,
                "Y": 0.14876818656921388,
                "Z": -0.5843492746353149
            },
            {
                "X": -0.036701202392578128,
                "Y": 0.14889812469482423,
                "Z": -0.5844203233718872
            },
            {
                "X": -0.03676891326904297,
                "Y": 0.1487865447998047,
                "Z": -0.5843592882156372
            },
            {
                "X": -0.03686022758483887,
                "Y": 0.14887404441833497,
                "Z": -0.5844322443008423
            },
            {
                "X": -0.036933183670043948,
                "Y": 0.1490015983581543,
                "Z": -0.584464430809021
            },
            {
                "X": -0.03690814971923828,
                "Y": 0.14910101890563966,
                "Z": -0.5846718549728394
            },
            {
                "X": -0.0369265079498291,
                "Y": 0.14920639991760255,
                "Z": -0.584839940071106
            },
            {
                "X": -0.03687572479248047,
                "Y": 0.14930009841918946,
                "Z": -0.5849906206130981
            },
            {
                "X": -0.0368952751159668,
                "Y": 0.14935612678527833,
                "Z": -0.5850976705551148
            },
            {
                "X": -0.03679370880126953,
                "Y": 0.14942121505737306,
                "Z": -0.5852292776107788
            },
            {
                "X": -0.03673744201660156,
                "Y": 0.14952754974365235,
                "Z": -0.5853427648544312
            },
            {
                "X": -0.036812543869018558,
                "Y": 0.14935588836669923,
                "Z": -0.5851820707321167
            },
            {
                "X": -0.036687612533569339,
                "Y": 0.14940190315246583,
                "Z": -0.5851925611495972
            },
            {
                "X": -0.03672599792480469,
                "Y": 0.14949703216552735,
                "Z": -0.5851486921310425
            },
            {
                "X": -0.03670334815979004,
                "Y": 0.14965200424194337,
                "Z": -0.5853525400161743
            },
            {
                "X": -0.03669118881225586,
                "Y": 0.14974308013916017,
                "Z": -0.585457444190979
            },
            {
                "X": -0.03657984733581543,
                "Y": 0.1497807502746582,
                "Z": -0.5856038331985474
            },
            {
                "X": -0.036447763442993167,
                "Y": 0.14994430541992188,
                "Z": -0.5859547853469849
            },
            {
                "X": -0.03627943992614746,
                "Y": 0.15003061294555665,
                "Z": -0.5861059427261353
            },
            {
                "X": -0.03614354133605957,
                "Y": 0.1501610279083252,
                "Z": -0.5863240957260132
            },
            {
                "X": -0.03608894348144531,
                "Y": 0.15021753311157227,
                "Z": -0.5864354372024536
            },
            {
                "X": -0.03609108924865723,
                "Y": 0.1503753662109375,
                "Z": -0.5866528749465942
            },
            {
                "X": -0.03610706329345703,
                "Y": 0.15048003196716309,
                "Z": -0.5867942571640015
            },
            {
                "X": -0.03623318672180176,
                "Y": 0.15045666694641114,
                "Z": -0.5867325067520142
            },
            {
                "X": -0.036229848861694339,
                "Y": 0.1505293846130371,
                "Z": -0.5868464708328247
            },
            {
                "X": -0.03628706932067871,
                "Y": 0.15073895454406739,
                "Z": -0.5868409872055054
            },
            {
                "X": -0.0363161563873291,
                "Y": 0.1508033275604248,
                "Z": -0.5868669748306274
            },
            {
                "X": -0.03615975379943848,
                "Y": 0.15100765228271485,
                "Z": -0.5871745347976685
            },
            {
                "X": -0.036086082458496097,
                "Y": 0.15130209922790528,
                "Z": -0.5874110460281372
            },
            {
                "X": -0.03602480888366699,
                "Y": 0.15154409408569337,
                "Z": -0.5876692533493042
            },
            {
                "X": -0.035866498947143558,
                "Y": 0.15195941925048829,
                "Z": -0.588218092918396
            },
            {
                "X": -0.03542017936706543,
                "Y": 0.15282082557678224,
                "Z": -0.5892642736434937
            },
            {
                "X": -0.035272836685180667,
                "Y": 0.15360808372497559,
                "Z": -0.5904229879379273
            },
            {
                "X": -0.03476738929748535,
                "Y": 0.1549224853515625,
                "Z": -0.5919517278671265
            },
            {
                "X": -0.03436088562011719,
                "Y": 0.15620827674865724,
                "Z": -0.5934299230575562
            },
            {
                "X": -0.03349876403808594,
                "Y": 0.15773844718933106,
                "Z": -0.5949617624282837
            },
            {
                "X": -0.03292679786682129,
                "Y": 0.16001224517822267,
                "Z": -0.5973840951919556
            },
            {
                "X": -0.03262138366699219,
                "Y": 0.16318726539611817,
                "Z": -0.6000102758407593
            },
            {
                "X": -0.0325627326965332,
                "Y": 0.16873860359191895,
                "Z": -0.6045528650283814
            },
            {
                "X": -0.03319907188415527,
                "Y": 0.1823582649230957,
                "Z": -0.617900013923645
            },
            {
                "X": -0.03373527526855469,
                "Y": 0.18946075439453126,
                "Z": -0.6257287263870239
            },
            {
                "X": -0.033429861068725589,
                "Y": 0.19676852226257325,
                "Z": -0.635036826133728
            },
            {
                "X": -0.03241229057312012,
                "Y": 0.2028045654296875,
                "Z": -0.6453722715377808
            },
            {
                "X": -0.03144550323486328,
                "Y": 0.20805907249450684,
                "Z": -0.6548894643783569
            },
            {
                "X": -0.029562950134277345,
                "Y": 0.20957136154174806,
                "Z": -0.6662048101425171
            },
            {
                "X": -0.02581477165222168,
                "Y": 0.20707917213439942,
                "Z": -0.6809946298599243
            },
            {
                "X": -0.022589683532714845,
                "Y": 0.20216655731201173,
                "Z": -0.695801854133606
            },
            {
                "X": -0.021830320358276368,
                "Y": 0.2006371021270752,
                "Z": -0.7087880373001099
            },
            {
                "X": -0.028370380401611329,
                "Y": 0.20287632942199708,
                "Z": -0.7169302701950073
            },
            {
                "X": -0.035135507583618167,
                "Y": 0.20424103736877442,
                "Z": -0.7266057729721069
            },
            {
                "X": -0.03931093215942383,
                "Y": 0.2050457000732422,
                "Z": -0.7398606538772583
            },
            {
                "X": -0.04146552085876465,
                "Y": 0.2024829387664795,
                "Z": -0.7554923295974731
            },
            {
                "X": -0.04331040382385254,
                "Y": 0.19800710678100587,
                "Z": -0.7751501798629761
            },
            {
                "X": -0.04545187950134277,
                "Y": 0.19601130485534669,
                "Z": -0.7922502756118774
            },
            {
                "X": -0.049372196197509769,
                "Y": 0.19355249404907227,
                "Z": -0.8093787431716919
            },
            {
                "X": -0.05443406105041504,
                "Y": 0.19192147254943849,
                "Z": -0.8256345987319946
            },
            {
                "X": -0.05888652801513672,
                "Y": 0.18966102600097657,
                "Z": -0.8429223299026489
            },
            {
                "X": -0.06245732307434082,
                "Y": 0.18654632568359376,
                "Z": -0.8629423379898071
            },
            {
                "X": -0.06600332260131836,
                "Y": 0.18381834030151368,
                "Z": -0.8822861909866333
            },
            {
                "X": -0.06964254379272461,
                "Y": 0.18055391311645509,
                "Z": -0.9030717611312866
            },
            {
                "X": -0.06964254379272461,
                "Y": 0.18055391311645509,
                "Z": -0.9030717611312866
            },
            {
                "X": -0.07725095748901367,
                "Y": 0.17571687698364259,
                "Z": -0.9467974901199341
            },
            {
                "X": -0.08144164085388184,
                "Y": 0.1734912395477295,
                "Z": -0.9687424898147583
            },
            {
                "X": -0.08517670631408692,
                "Y": 0.17140579223632813,
                "Z": -0.9911412000656128
            },
            {
                "X": -0.0894160270690918,
                "Y": 0.16901421546936036,
                "Z": -1.0137749910354615
            },
            {
                "X": -0.09362673759460449,
                "Y": 0.16745543479919434,
                "Z": -1.0370787382125855
            },
            {
                "X": -0.09771609306335449,
                "Y": 0.16581201553344727,
                "Z": -1.0603176355361939
            },
            {
                "X": -0.10217905044555664,
                "Y": 0.16435790061950684,
                "Z": -1.083346962928772
            },
            {
                "X": -0.10660171508789063,
                "Y": 0.16350364685058595,
                "Z": -1.1069437265396119
            },
            {
                "X": -0.10660171508789063,
                "Y": 0.16350364685058595,
                "Z": -1.1069437265396119
            },
            {
                "X": -0.11100935935974121,
                "Y": 0.16270971298217774,
                "Z": -1.1307226419448853
            },
            {
                "X": -0.11592602729797363,
                "Y": 0.1623227596282959,
                "Z": -1.1536284685134888
            },
            {
                "X": -0.12128615379333496,
                "Y": 0.1612842082977295,
                "Z": -1.1760340929031373
            },
            {
                "X": -0.12665271759033204,
                "Y": 0.16064906120300294,
                "Z": -1.1985212564468384
            },
            {
                "X": -0.13190031051635743,
                "Y": 0.159898042678833,
                "Z": -1.2202321290969849
            },
            {
                "X": -0.13779211044311524,
                "Y": 0.15899157524108888,
                "Z": -1.241369605064392
            },
            {
                "X": -0.14363455772399903,
                "Y": 0.1572265625,
                "Z": -1.2615288496017457
            },
            {
                "X": -0.14945387840270997,
                "Y": 0.15555381774902345,
                "Z": -1.2807914018630982
            },
            {
                "X": -0.1554884910583496,
                "Y": 0.154022216796875,
                "Z": -1.300125002861023
            },
            {
                "X": -0.1613631248474121,
                "Y": 0.15417098999023438,
                "Z": -1.3184272050857545
            },
            {
                "X": -0.16709637641906739,
                "Y": 0.155928373336792,
                "Z": -1.3360785245895386
            },
            {
                "X": -0.17309927940368653,
                "Y": 0.1571369171142578,
                "Z": -1.3528836965560914
            },
            {
                "X": -0.17892241477966309,
                "Y": 0.15729117393493653,
                "Z": -1.367862582206726
            },
            {
                "X": -0.18465423583984376,
                "Y": 0.15684866905212403,
                "Z": -1.3817440271377564
            },
            {
                "X": -0.19054889678955079,
                "Y": 0.15562748908996583,
                "Z": -1.396292805671692
            },
            {
                "X": -0.19562149047851563,
                "Y": 0.1543715000152588,
                "Z": -1.4098345041275025
            },
            {
                "X": -0.20026302337646485,
                "Y": 0.1528162956237793,
                "Z": -1.4233003854751588
            },
            {
                "X": -0.20519137382507325,
                "Y": 0.15021991729736329,
                "Z": -1.4360319375991822
            },
            {
                "X": -0.21002507209777833,
                "Y": 0.1478877067565918,
                "Z": -1.4481912851333619
            },
            {
                "X": -0.21392297744750977,
                "Y": 0.14511489868164063,
                "Z": -1.4599543809890748
            },
            {
                "X": -0.21726727485656739,
                "Y": 0.1415095329284668,
                "Z": -1.4695993661880494
            },
            {
                "X": -0.22095441818237306,
                "Y": 0.1379401683807373,
                "Z": -1.4793354272842408
            },
            {
                "X": -0.2221677303314209,
                "Y": 0.13421225547790528,
                "Z": -1.485803484916687
            },
            {
                "X": -0.22264695167541505,
                "Y": 0.13275623321533204,
                "Z": -1.4903548955917359
            },
            {
                "X": -0.22263336181640626,
                "Y": 0.13321900367736817,
                "Z": -1.4930726289749146
            },
            {
                "X": -0.22163939476013184,
                "Y": 0.13161849975585938,
                "Z": -1.4902735948562623
            },
            {
                "X": -0.22504329681396485,
                "Y": 0.1298203468322754,
                "Z": -1.48824942111969
            },
            {
                "X": -0.22898244857788087,
                "Y": 0.13588905334472657,
                "Z": -1.4942160844802857
            },
            {
                "X": -0.23315811157226563,
                "Y": 0.13846278190612794,
                "Z": -1.4987713098526
            },
            {
                "X": -0.23366904258728028,
                "Y": 0.13614749908447267,
                "Z": -1.4989322423934937
            },
            {
                "X": -0.23536419868469239,
                "Y": 0.13632965087890626,
                "Z": -1.501843810081482
            },
            {
                "X": -0.23641729354858399,
                "Y": 0.13756442070007325,
                "Z": -1.5063384771347047
            },
            {
                "X": -0.23661351203918458,
                "Y": 0.13715171813964845,
                "Z": -1.5058382749557496
            },
            {
                "X": -0.23838114738464356,
                "Y": 0.13800716400146485,
                "Z": -1.5059930086135865
            },
            {
                "X": -0.2398056983947754,
                "Y": 0.13889217376708985,
                "Z": -1.5067235231399537
            },
            {
                "X": -0.23934340476989747,
                "Y": 0.13902783393859864,
                "Z": -1.5063236951828004
            },
            {
                "X": -0.23945140838623048,
                "Y": 0.1390516757965088,
                "Z": -1.5074087381362916
            },
            {
                "X": -0.23842835426330567,
                "Y": 0.13864398002624513,
                "Z": -1.508541464805603
            },
            {
                "X": -0.23744583129882813,
                "Y": 0.13843917846679688,
                "Z": -1.5080119371414185
            },
            {
                "X": -0.237640380859375,
                "Y": 0.13867402076721192,
                "Z": -1.5079702138900757
            },
            {
                "X": -0.23756718635559083,
                "Y": 0.1387636661529541,
                "Z": -1.5088831186294556
            },
            {
                "X": -0.23766756057739259,
                "Y": 0.13886117935180665,
                "Z": -1.5092684030532838
            },
            {
                "X": -0.23815011978149415,
                "Y": 0.13900351524353028,
                "Z": -1.5092090368270875
            },
            {
                "X": -0.23824524879455567,
                "Y": 0.13905096054077149,
                "Z": -1.5094939470291138
            },
            {
                "X": -0.2379467487335205,
                "Y": 0.13909912109375,
                "Z": -1.5093384981155396
            },
            {
                "X": -0.23807787895202638,
                "Y": 0.13907814025878907,
                "Z": -1.5092617273330689
            },
            {
                "X": -0.23792314529418946,
                "Y": 0.13904976844787599,
                "Z": -1.5093141794204713
            },
            {
                "X": -0.23771929740905763,
                "Y": 0.13909482955932618,
                "Z": -1.5091513395309449
            },
            {
                "X": -0.23777222633361817,
                "Y": 0.13906288146972657,
                "Z": -1.5090214014053345
            },
            {
                "X": -0.23775315284729005,
                "Y": 0.1391134262084961,
                "Z": -1.5088728666305543
            },
            {
                "X": -0.23769068717956544,
                "Y": 0.1391613483428955,
                "Z": -1.5087882280349732
            },
            {
                "X": -0.23757624626159669,
                "Y": 0.13910341262817384,
                "Z": -1.5088196992874146
            },
            {
                "X": -0.2375338077545166,
                "Y": 0.139143705368042,
                "Z": -1.5087834596633912
            },
            {
                "X": -0.23737502098083497,
                "Y": 0.13918185234069825,
                "Z": -1.5086923837661744
            },
            {
                "X": -0.23740220069885255,
                "Y": 0.13904428482055665,
                "Z": -1.5085982084274293
            },
            {
                "X": -0.23735594749450684,
                "Y": 0.13909697532653809,
                "Z": -1.508583664894104
            },
            {
                "X": -0.2372148036956787,
                "Y": 0.13889288902282716,
                "Z": -1.5086990594863892
            },
            {
                "X": -0.23714804649353028,
                "Y": 0.13891959190368653,
                "Z": -1.5087209939956666
            },
            {
                "X": -0.23709416389465333,
                "Y": 0.13897037506103517,
                "Z": -1.5087283849716187
            },
            {
                "X": -0.23697638511657716,
                "Y": 0.1390705108642578,
                "Z": -1.508809208869934
            },
            {
                "X": -0.23695755004882813,
                "Y": 0.13892841339111329,
                "Z": -1.50887930393219
            },
            {
                "X": -0.23690176010131837,
                "Y": 0.13903474807739259,
                "Z": -1.5090252161026
            },
            {
                "X": -0.2369849681854248,
                "Y": 0.13889646530151368,
                "Z": -1.5088776350021363
            },
            {
                "X": -0.23563337326049806,
                "Y": 0.14049601554870606,
                "Z": -1.509987235069275
            },
            {
                "X": -0.23691439628601075,
                "Y": 0.13867974281311036,
                "Z": -1.5087627172470093
            },
            {
                "X": -0.23688459396362306,
                "Y": 0.13869595527648927,
                "Z": -1.5087400674819947
            },
            {
                "X": -0.23681402206420899,
                "Y": 0.13872408866882325,
                "Z": -1.5087610483169556
            },
            {
                "X": -0.23680806159973145,
                "Y": 0.1385807991027832,
                "Z": -1.5086737871170045
            },
            {
                "X": -0.23669123649597169,
                "Y": 0.1385660171508789,
                "Z": -1.508689522743225
            },
            {
                "X": -0.23674988746643067,
                "Y": 0.13853693008422852,
                "Z": -1.508750557899475
            },
            {
                "X": -0.23674392700195313,
                "Y": 0.13845586776733399,
                "Z": -1.508656620979309
            }
        ]
    }
}